{"assets":{"3684D5839E9C8B8F60E54E23AE5AD9E0":{"type":"texture","index":3,"url":{"native":"assets\/997F3722-87B7-47E2-9505-749650752FC7.pdf"},"width":285,"height":27},"7FD96FD65160E41977E3C562FFAC604F":{"type":"texture","index":0,"url":{"native":"assets\/997F3722-87B7-47E2-9505-749650752FC7.pdf"},"width":1280,"height":720},"798371265ACC3F0078BD72F6415D6C45":{"type":"texture","index":1,"url":{"native":"assets\/997F3722-87B7-47E2-9505-749650752FC7.pdf"},"width":1108,"height":623},"1640D959D5A14BFE1A85D0214E13A49E":{"type":"texture","index":9,"url":{"native":"assets\/997F3722-87B7-47E2-9505-749650752FC7.pdf"},"width":1280,"height":720},"189C5E49B99203DADCBAF1216F7B1754":{"type":"texture","index":6,"url":{"native":"assets\/997F3722-87B7-47E2-9505-749650752FC7.pdf"},"width":1108,"height":623},"5F1BA05A16DB77A525DA9A92B585368F":{"type":"texture","index":8,"url":{"native":"assets\/997F3722-87B7-47E2-9505-749650752FC7.pdf"},"width":1280,"height":720},"DE3A73E8771A447D87E589B2965312EC":{"type":"texture","index":2,"url":{"native":"assets\/997F3722-87B7-47E2-9505-749650752FC7.pdf"},"width":218,"height":132},"4631567C1084A0418A19BC2EED6E0F51":{"type":"texture","index":5,"url":{"native":"assets\/997F3722-87B7-47E2-9505-749650752FC7.pdf"},"width":220,"height":185},"DDE4FE84D85B915C09CDEAC2ADC7655C":{"type":"texture","index":4,"url":{"native":"assets\/997F3722-87B7-47E2-9505-749650752FC7.pdf"},"width":988,"height":42},"troye sivan 1.mp4-5.5656-12.1306":{"type":"video","index":0,"url":{"web":"assets\/troye sivan 1.mp4-5.5656-12.1306.mp4","native":"assets\/troye sivan 1.mp4-5.5656-12.1306.mp4"},"width":1920,"height":1080},"F69E00F5F7CB58EDB999D19FA6E15EAE":{"type":"texture","index":7,"url":{"native":"assets\/997F3722-87B7-47E2-9505-749650752FC7.pdf"},"width":1107.5556640625,"height":623}},"events":[{"effects":[{"beginTime":0,"baseLayer":{"animations":[],"initialState":{"affineTransform":[1,0,0,1,0,0],"masksToBounds":false,"rotation":0,"scale":1,"position":{"pointX":558.48295259475708,"pointY":360},"width":1108,"sublayerTransform":[1,0,0,0,0,1,0,0,0,0,1,0,0,0,0,1],"contentsRect":{"y":0,"x":0,"width":1,"height":1},"opacity":1,"edgeAntialiasingMask":251658240,"height":623,"hidden":false,"anchorPoint":{"pointX":0.5,"pointY":0.5}},"objectID":"A3289D50-6F74-4CEE-AF49-89B7488E7B8D","layers":[{"animations":[],"initialState":{"affineTransform":[1,0,0,1,0,0],"masksToBounds":false,"rotation":0,"scale":1,"position":{"pointX":635.51704740524292,"pointY":311.5},"width":1108,"sublayerTransform":[1,0,0,0,0,1,0,0,0,0,1,-0.0005251186870016398,0,0,0,1],"contentsRect":{"y":0,"x":0,"width":1,"height":1},"opacity":1,"edgeAntialiasingMask":251658240,"height":623,"hidden":false,"anchorPoint":{"pointX":0.57357134242350449,"pointY":0.5}},"layers":[{"animations":[{"additive":false,"timeOffset":0,"beginTime":1e-100,"repeatCount":0,"fillMode":"both","duration":0.001,"autoreverses":false,"animations":[{"additive":false,"timeOffset":0,"beginTime":0,"from":{"scalar":false},"repeatCount":0,"fillMode":"removed","duration":0.001,"autoreverses":false,"property":"hidden","to":{"scalar":false},"removedOnCompletion":true},{"additive":false,"timeOffset":0,"beginTime":0,"from":{"scalar":true},"repeatCount":0,"fillMode":"removed","duration":0.001,"autoreverses":false,"property":"isPlaying","to":{"scalar":true},"removedOnCompletion":true}],"removedOnCompletion":false}],"layers":[],"texturedRectangle":{"isBackgroundTexture":true,"singleTextureOpacity":1,"textureType":5,"textBaseline":0,"textXHeight":0,"isVerticalText":false},"initialState":{"affineTransform":[1,0,0,1,0,0],"masksToBounds":false,"rotation":0,"scale":1,"position":{"pointX":553.51704740524292,"pointY":312},"width":1108,"sublayerTransform":[1,0,0,0,0,1,0,0,0,0,1,0,0,0,0,1],"contentsRect":{"y":0,"x":0,"width":1,"height":1},"opacity":1,"edgeAntialiasingMask":0,"height":623,"hidden":false,"anchorPoint":{"pointX":0.5,"pointY":0.5}},"texture":"798371265ACC3F0078BD72F6415D6C45"}]}]},"effects":[{"beginTime":0,"baseLayer":{"animations":[],"initialState":{"affineTransform":[1,0,0,1,0,0],"masksToBounds":false,"rotation":0,"scale":1,"position":{"pointX":558.26078462600708,"pointY":360},"width":1107.5556640625,"sublayerTransform":[1,0,0,0,0,1,0,0,0,0,1,0,0,0,0,1],"contentsRect":{"y":0,"x":0,"width":1,"height":1},"opacity":1,"edgeAntialiasingMask":251658240,"height":623,"hidden":false,"anchorPoint":{"pointX":0.5,"pointY":0.5}},"objectID":"A3289D50-6F74-4CEE-AF49-89B7488E7B8D","layers":[{"animations":[],"layers":[],"texturedRectangle":{"isBackgroundTexture":true,"singleTextureOpacity":1,"textureType":5,"textBaseline":0,"textXHeight":0,"isVerticalText":false},"initialState":{"affineTransform":[1,0,0,1,0,0],"masksToBounds":false,"rotation":0,"scale":1,"position":{"pointX":553.51704740524292,"pointY":312},"width":1108,"sublayerTransform":[1,0,0,0,0,1,0,0,0,0,1,0,0,0,0,1],"contentsRect":{"y":0,"x":0,"width":1,"height":1},"opacity":1,"edgeAntialiasingMask":0,"height":623,"hidden":true,"anchorPoint":{"pointX":0.5,"pointY":0.5}},"texture":"189C5E49B99203DADCBAF1216F7B1754"},{"animations":[],"layers":[],"isVideoLayer":true,"initialState":{"affineTransform":[1,0,0,1,0,0],"masksToBounds":false,"rotation":0,"scale":1,"position":{"pointX":553.77783203125,"pointY":311.5},"width":1107.5556640625,"sublayerTransform":[1,0,0,0,0,1,0,0,0,0,1,0,0,0,0,1],"contentsRect":{"y":0,"x":0,"width":1,"height":1},"opacity":1,"edgeAntialiasingMask":251658240,"height":623,"hidden":false,"anchorPoint":{"pointX":0.5,"pointY":0.5}},"texture":"F69E00F5F7CB58EDB999D19FA6E15EAE"}]},"effects":[],"movie":{"volume":0,"isStreaming":false,"isAudioOnly":false,"endTime":12.130621910095215,"startTime":5.5656442642211914,"asset":"troye sivan 1.mp4-5.5656-12.1306","loopMode":"looping"},"duration":0,"type":"buildIn","attributes":{"direction":0},"name":"renderMovie","objectID":"A3289D50-6F74-4CEE-AF49-89B7488E7B8D"}],"duration":0.001,"type":"buildIn","attributes":{"direction":0},"name":"apple:movie-start","objectID":"A3289D50-6F74-4CEE-AF49-89B7488E7B8D"}],"automaticPlay":true,"hyperlinks":[],"accessibility":[{"text":"Possession.1981.1080p.BRRip.x264.AAC-ETRG.mp4_00_29_2800004.jpg","targetRectangle":{"y":202.5294189453125,"x":1059.01708984375,"width":215.71875,"height":129.4375}},{"text":"pasted-movie.heic","targetRectangle":{"y":338.06559944152832,"x":1058.23583984375,"width":217.28889465332031,"height":182.85507500634412}},{"text":"Los pacientes llegan con las marcas de sus relaciones pasadas. Algunos tienen partes quemadas, otros todavía siguen en llamas en ciertos lugares. El fuego representa los traumas y cicatrices que dejaron sus vínculos.","targetRectangle":{"y":621.20422393083572,"x":185.40812182426453,"width":990.03600000000006,"height":42}},{"text":"LOS PACIENTES","targetRectangle":{"y":36.575355470180511,"x":33.976244688034058,"width":285.35999999999996,"height":35}}],"baseLayer":{"animations":[],"initialState":{"affineTransform":[1,0,0,1,0,0],"masksToBounds":false,"rotation":0,"scale":1,"position":{"pointX":640,"pointY":360},"width":1280,"sublayerTransform":[1,0,0,0,0,1,0,0,0,0,1,0,0,0,0,1],"contentsRect":{"y":0,"x":0,"width":1,"height":1},"opacity":1,"edgeAntialiasingMask":251658240,"height":720,"hidden":false,"anchorPoint":{"pointX":0.5,"pointY":0.5}},"layers":[{"animations":[],"initialState":{"affineTransform":[1,0,0,1,0,0],"masksToBounds":false,"rotation":0,"scale":1,"position":{"pointX":640,"pointY":360},"width":1280,"sublayerTransform":[1,0,0,0,0,1,0,0,0,0,1,0,0,0,0,1],"contentsRect":{"y":0,"x":0,"width":1,"height":1},"opacity":1,"edgeAntialiasingMask":251658240,"height":720,"hidden":false,"anchorPoint":{"pointX":0.5,"pointY":0.5}},"layers":[{"animations":[],"initialState":{"affineTransform":[1,0,0,1,0,0],"masksToBounds":false,"rotation":0,"scale":1,"position":{"pointX":640,"pointY":360},"width":1280,"sublayerTransform":[1,0,0,0,0,1,0,0,0,0,1,0,0,0,0,1],"contentsRect":{"y":0,"x":0,"width":1,"height":1},"opacity":1,"edgeAntialiasingMask":251658240,"height":720,"hidden":false,"anchorPoint":{"pointX":0.5,"pointY":0.5}},"layers":[{"animations":[],"layers":[],"texturedRectangle":{"isBackgroundTexture":true,"singleTextureOpacity":1,"textureType":1,"textBaseline":0,"textXHeight":0,"isVerticalText":false},"initialState":{"affineTransform":[1,0,0,1,0,0],"masksToBounds":false,"rotation":0,"scale":1,"position":{"pointX":640,"pointY":360},"width":1280,"sublayerTransform":[1,0,0,0,0,1,0,0,0,0,1,0,0,0,0,1],"contentsRect":{"y":0,"x":0,"width":1,"height":1},"opacity":1,"edgeAntialiasingMask":0,"height":720,"hidden":false,"anchorPoint":{"pointX":0.5,"pointY":0.5}},"texture":"7FD96FD65160E41977E3C562FFAC604F"}]}]},{"animations":[],"initialState":{"affineTransform":[1,0,0,1,0,0],"masksToBounds":false,"rotation":0,"scale":1,"position":{"pointX":640,"pointY":360},"width":1280,"sublayerTransform":[1,0,0,0,0,1,0,0,0,0,1,0,0,0,0,1],"contentsRect":{"y":0,"x":0,"width":1,"height":1},"opacity":1,"edgeAntialiasingMask":251658240,"height":720,"hidden":false,"anchorPoint":{"pointX":0.5,"pointY":0.5}},"layers":[{"animations":[],"initialState":{"affineTransform":[1,0,0,1,0,0],"masksToBounds":false,"rotation":0,"scale":1,"position":{"pointX":558.48295259475708,"pointY":360},"width":1108,"sublayerTransform":[1,0,0,0,0,1,0,0,0,0,1,0,0,0,0,1],"contentsRect":{"y":0,"x":0,"width":1,"height":1},"opacity":1,"edgeAntialiasingMask":251658240,"height":623,"hidden":false,"anchorPoint":{"pointX":0.5,"pointY":0.5}},"objectID":"A3289D50-6F74-4CEE-AF49-89B7488E7B8D","layers":[{"animations":[],"layers":[],"texturedRectangle":{"isBackgroundTexture":true,"singleTextureOpacity":1,"textureType":5,"textBaseline":0,"textXHeight":0,"isVerticalText":false},"initialState":{"affineTransform":[1,0,0,1,0,0],"masksToBounds":false,"rotation":0,"scale":1,"position":{"pointX":553.51704740524292,"pointY":312},"width":1108,"sublayerTransform":[1,0,0,0,0,1,0,0,0,0,1,0,0,0,0,1],"contentsRect":{"y":0,"x":0,"width":1,"height":1},"opacity":1,"edgeAntialiasingMask":0,"height":623,"hidden":false,"anchorPoint":{"pointX":0.5,"pointY":0.5}},"texture":"798371265ACC3F0078BD72F6415D6C45"}]}]},{"animations":[],"initialState":{"affineTransform":[1,0,0,1,0,0],"masksToBounds":false,"rotation":0,"scale":1,"position":{"pointX":640,"pointY":360},"width":1280,"sublayerTransform":[1,0,0,0,0,1,0,0,0,0,1,0,0,0,0,1],"contentsRect":{"y":0,"x":0,"width":1,"height":1},"opacity":1,"edgeAntialiasingMask":251658240,"height":720,"hidden":false,"anchorPoint":{"pointX":0.5,"pointY":0.5}},"layers":[{"animations":[],"initialState":{"affineTransform":[1,0,0,1,0,0],"masksToBounds":false,"rotation":0,"scale":1,"position":{"pointX":1168.01708984375,"pointY":268.5294189453125},"width":218,"sublayerTransform":[1,0,0,0,0,1,0,0,0,0,1,0,0,0,0,1],"contentsRect":{"y":0,"x":0,"width":1,"height":1},"opacity":1,"edgeAntialiasingMask":251658240,"height":132,"hidden":false,"anchorPoint":{"pointX":0.5,"pointY":0.5}},"layers":[{"animations":[],"layers":[],"texturedRectangle":{"isBackgroundTexture":true,"singleTextureOpacity":1,"textureType":5,"textBaseline":0,"textXHeight":0,"isVerticalText":false},"initialState":{"affineTransform":[1,0,0,1,0,0],"masksToBounds":false,"rotation":0,"scale":1,"position":{"pointX":107.98291015625,"pointY":64.4705810546875},"width":218,"sublayerTransform":[1,0,0,0,0,1,0,0,0,0,1,0,0,0,0,1],"contentsRect":{"y":0,"x":0,"width":1,"height":1},"opacity":1,"edgeAntialiasingMask":0,"height":132,"hidden":false,"anchorPoint":{"pointX":0.5,"pointY":0.5}},"texture":"DE3A73E8771A447D87E589B2965312EC"}]}]},{"animations":[],"initialState":{"affineTransform":[1,0,0,1,0,0],"masksToBounds":false,"rotation":0,"scale":1,"position":{"pointX":640,"pointY":360},"width":1280,"sublayerTransform":[1,0,0,0,0,1,0,0,0,0,1,0,0,0,0,1],"contentsRect":{"y":0,"x":0,"width":1,"height":1},"opacity":1,"edgeAntialiasingMask":251658240,"height":720,"hidden":false,"anchorPoint":{"pointX":0.5,"pointY":0.5}},"layers":[{"animations":[],"initialState":{"affineTransform":[1,0,0,1,0,0],"masksToBounds":false,"rotation":0,"scale":1,"position":{"pointX":173.80957794189453,"pointY":47.408688724040985},"width":285,"sublayerTransform":[1,0,0,0,0,1,0,0,0,0,1,0,0,0,0,1],"contentsRect":{"y":0,"x":0,"width":1,"height":1},"opacity":1,"edgeAntialiasingMask":251658240,"height":27,"hidden":false,"anchorPoint":{"pointX":0.5,"pointY":0.5}},"layers":[{"animations":[],"layers":[],"texturedRectangle":{"singleTextureOpacity":1,"textXHeight":0.54222222222222216,"textBaseline":0.90834596973878368,"isBackgroundTexture":true,"isVerticalText":false,"textColor":[0.9999966025352478,0.99999994039535522,0.99999994039535522,1],"textureType":6},"initialState":{"affineTransform":[1,0,0,1,0,0],"masksToBounds":false,"rotation":0,"scale":1,"position":{"pointX":146.19042205810547,"pointY":19.591311275959015},"width":285,"sublayerTransform":[1,0,0,0,0,1,0,0,0,0,1,0,0,0,0,1],"contentsRect":{"y":0,"x":0,"width":1,"height":1},"opacity":1,"edgeAntialiasingMask":0,"height":27,"hidden":false,"anchorPoint":{"pointX":0.5,"pointY":0.5}},"texture":"3684D5839E9C8B8F60E54E23AE5AD9E0"}]}]},{"animations":[],"initialState":{"affineTransform":[1,0,0,1,0,0],"masksToBounds":false,"rotation":0,"scale":1,"position":{"pointX":640,"pointY":360},"width":1280,"sublayerTransform":[1,0,0,0,0,1,0,0,0,0,1,0,0,0,0,1],"contentsRect":{"y":0,"x":0,"width":1,"height":1},"opacity":1,"edgeAntialiasingMask":251658240,"height":720,"hidden":false,"anchorPoint":{"pointX":0.5,"pointY":0.5}},"layers":[{"animations":[],"initialState":{"affineTransform":[1,0,0,1,0,0],"masksToBounds":false,"rotation":0,"scale":1,"position":{"pointX":676.741455078125,"pointY":639.5375571846962},"width":988,"sublayerTransform":[1,0,0,0,0,1,0,0,0,0,1,0,0,0,0,1],"contentsRect":{"y":0,"x":0,"width":1,"height":1},"opacity":1,"edgeAntialiasingMask":251658240,"height":42,"hidden":false,"anchorPoint":{"pointX":0.5,"pointY":0.5}},"layers":[{"animations":[],"layers":[],"texturedRectangle":{"singleTextureOpacity":1,"textXHeight":0.20185714285714285,"textBaseline":0.85738608170123332,"isBackgroundTexture":true,"isVerticalText":false,"textColor":[0.9999966025352478,0.99999994039535522,0.99999994039535522,1],"textureType":6},"initialState":{"affineTransform":[1,0,0,1,0,0],"masksToBounds":false,"rotation":0,"scale":1,"position":{"pointX":495.258544921875,"pointY":25.462442815303802},"width":988,"sublayerTransform":[1,0,0,0,0,1,0,0,0,0,1,0,0,0,0,1],"contentsRect":{"y":0,"x":0,"width":1,"height":1},"opacity":1,"edgeAntialiasingMask":0,"height":42,"hidden":false,"anchorPoint":{"pointX":0.5,"pointY":0.5}},"texture":"DDE4FE84D85B915C09CDEAC2ADC7655C"}]}]},{"animations":[],"initialState":{"affineTransform":[1,0,0,1,0,0],"masksToBounds":false,"rotation":0,"scale":1,"position":{"pointX":640,"pointY":360},"width":1280,"sublayerTransform":[1,0,0,0,0,1,0,0,0,0,1,0,0,0,0,1],"contentsRect":{"y":0,"x":0,"width":1,"height":1},"opacity":1,"edgeAntialiasingMask":251658240,"height":720,"hidden":false,"anchorPoint":{"pointX":0.5,"pointY":0.5}},"layers":[{"animations":[],"initialState":{"affineTransform":[1,0,0,1,0,0],"masksToBounds":false,"rotation":0,"scale":1,"position":{"pointX":1168.23583984375,"pointY":430.56559944152832},"width":220,"sublayerTransform":[1,0,0,0,0,1,0,0,0,0,1,0,0,0,0,1],"contentsRect":{"y":0,"x":0,"width":1,"height":1},"opacity":1,"edgeAntialiasingMask":251658240,"height":185,"hidden":false,"anchorPoint":{"pointX":0.5,"pointY":0.5}},"layers":[{"animations":[],"layers":[],"texturedRectangle":{"isBackgroundTexture":true,"singleTextureOpacity":1,"textureType":5,"textBaseline":0,"textXHeight":0,"isVerticalText":false},"initialState":{"affineTransform":[1,0,0,1,0,0],"masksToBounds":false,"rotation":0,"scale":1,"position":{"pointX":108.76416015625,"pointY":91.43440055847168},"width":220,"sublayerTransform":[1,0,0,0,0,1,0,0,0,0,1,0,0,0,0,1],"contentsRect":{"y":0,"x":0,"width":1,"height":1},"opacity":1,"edgeAntialiasingMask":0,"height":185,"hidden":false,"anchorPoint":{"pointX":0.5,"pointY":0.5}},"texture":"4631567C1084A0418A19BC2EED6E0F51"}]}]}]}},{"effects":[{"beginTime":0,"baseLayer":{"animations":[],"initialState":{"affineTransform":[1,0,0,1,0,0],"masksToBounds":false,"rotation":0,"scale":1,"position":{"pointX":640,"pointY":360},"width":1280,"sublayerTransform":[1,0,0,0,0,1,0,0,0,0,1,0,0,0,0,1],"contentsRect":{"y":0,"x":0,"width":1,"height":1},"opacity":1,"edgeAntialiasingMask":251658240,"height":720,"hidden":false,"anchorPoint":{"pointX":0.5,"pointY":0.5}},"objectID":"0","layers":[{"animations":[],"initialState":{"affineTransform":[1,0,0,1,0,0],"masksToBounds":false,"rotation":0,"scale":1,"position":{"pointX":640,"pointY":360},"width":1280,"sublayerTransform":[1,0,0,0,0,1,0,0,0,0,1,-0.0005251186870016398,0,0,0,1],"contentsRect":{"y":0,"x":0,"width":1,"height":1},"opacity":1,"edgeAntialiasingMask":251658240,"height":720,"hidden":false,"anchorPoint":{"pointX":0.5,"pointY":0.5}},"layers":[{"animations":[],"layers":[],"texturedRectangle":{"isBackgroundTexture":false,"singleTextureOpacity":1,"textureType":0,"textBaseline":0,"textXHeight":0,"isVerticalText":false},"initialState":{"affineTransform":[1,0,0,1,0,0],"masksToBounds":false,"rotation":0,"scale":1,"position":{"pointX":640,"pointY":360},"width":1280,"sublayerTransform":[1,0,0,0,0,1,0,0,0,0,1,0,0,0,0,1],"contentsRect":{"y":0,"x":0,"width":1,"height":1},"opacity":1,"edgeAntialiasingMask":0,"height":720,"hidden":false,"anchorPoint":{"pointX":0.5,"pointY":0.5}},"texture":"1640D959D5A14BFE1A85D0214E13A49E"},{"animations":[{"additive":false,"timeOffset":0,"beginTime":0,"from":{"scalar":false},"repeatCount":0,"fillMode":"both","duration":0.001,"autoreverses":false,"property":"hidden","to":{"scalar":true},"removedOnCompletion":false}],"layers":[],"texturedRectangle":{"isBackgroundTexture":false,"singleTextureOpacity":1,"textureType":0,"textBaseline":0,"textXHeight":0,"isVerticalText":false},"initialState":{"affineTransform":[1,0,0,1,0,0],"masksToBounds":false,"rotation":0,"scale":1,"position":{"pointX":640,"pointY":360},"width":1280,"sublayerTransform":[1,0,0,0,0,1,0,0,0,0,1,0,0,0,0,1],"contentsRect":{"y":0,"x":0,"width":1,"height":1},"opacity":1,"edgeAntialiasingMask":0,"height":720,"hidden":false,"anchorPoint":{"pointX":0.5,"pointY":0.5}},"texture":"5F1BA05A16DB77A525DA9A92B585368F"}]}]},"effects":[],"duration":0.001,"type":"transition","attributes":{"direction":0},"name":"none","objectID":"0"}],"automaticPlay":false,"hyperlinks":[],"accessibility":[{"text":"Possession.1981.1080p.BRRip.x264.AAC-ETRG.mp4_00_29_2800004.jpg","targetRectangle":{"y":202.5294189453125,"x":1059.01708984375,"width":215.71875,"height":129.4375}},{"text":"pasted-movie.heic","targetRectangle":{"y":338.06559944152832,"x":1058.23583984375,"width":217.28889465332031,"height":182.85507500634412}},{"text":"Los pacientes llegan con las marcas de sus relaciones pasadas. Algunos tienen partes quemadas, otros todavía siguen en llamas en ciertos lugares. El fuego representa los traumas y cicatrices que dejaron sus vínculos.","targetRectangle":{"y":621.20422393083572,"x":185.40812182426453,"width":990.03600000000006,"height":42}},{"text":"LOS PACIENTES","targetRectangle":{"y":36.575355470180511,"x":33.976244688034058,"width":285.35999999999996,"height":35}},{"text":"troye sivan 1.mp4","targetRectangle":{"y":48.5,"x":4.4829525947570801,"width":1107.5556640625,"height":623}}],"baseLayer":{"animations":[],"initialState":{"affineTransform":[1,0,0,1,0,0],"masksToBounds":false,"rotation":0,"scale":1,"position":{"pointX":640,"pointY":360},"width":1280,"sublayerTransform":[1,0,0,0,0,1,0,0,0,0,1,0,0,0,0,1],"contentsRect":{"y":0,"x":0,"width":1,"height":1},"opacity":1,"edgeAntialiasingMask":251658240,"height":720,"hidden":false,"anchorPoint":{"pointX":0.5,"pointY":0.5}},"objectID":"0","layers":[{"animations":[],"initialState":{"affineTransform":[1,0,0,1,0,0],"masksToBounds":false,"rotation":0,"scale":1,"position":{"pointX":640,"pointY":360},"width":1280,"sublayerTransform":[1,0,0,0,0,1,0,0,0,0,1,-0.0005251186870016398,0,0,0,1],"contentsRect":{"y":0,"x":0,"width":1,"height":1},"opacity":1,"edgeAntialiasingMask":251658240,"height":720,"hidden":false,"anchorPoint":{"pointX":0.5,"pointY":0.5}},"layers":[{"animations":[],"layers":[],"texturedRectangle":{"isBackgroundTexture":false,"singleTextureOpacity":1,"textureType":0,"textBaseline":0,"textXHeight":0,"isVerticalText":false},"initialState":{"affineTransform":[1,0,0,1,0,0],"masksToBounds":false,"rotation":0,"scale":1,"position":{"pointX":640,"pointY":360},"width":1280,"sublayerTransform":[1,0,0,0,0,1,0,0,0,0,1,0,0,0,0,1],"contentsRect":{"y":0,"x":0,"width":1,"height":1},"opacity":1,"edgeAntialiasingMask":0,"height":720,"hidden":false,"anchorPoint":{"pointX":0.5,"pointY":0.5}},"texture":"5F1BA05A16DB77A525DA9A92B585368F"}]}]}}]}